sage/__init__.py
sage/clone.py
sage/folder_structure_view.py
sage_directory/__init__.py
sage_directory/clone.py
sage_directory/folder_structure_view.py
sage_directory-0.0.8.dist-info/METADATA
sage_directory-0.0.8.dist-info/WHEEL
sage_directory-0.0.8.dist-info/top_level.txt
sage_directory-0.0.8.dist-info/RECORD
