Metadata-Version: 2.1
Name: sage-directory
Version: 0.0.8
Summary: sage-directory is a python package that offers a detailed overview of folder contents and streamlines the process of copying and managing directories.
Home-page: https://github.com/maxineattobrah/sage-directory
Author: Maxine Attobrah
Author-email: maxineattobrah@gmail.com
Keywords: python,folder overview,folder management,folder analysis,batch operations,data science utility,data engineering utility,IT operations
Platform: any
Classifier: Intended Audience :: Developers
Classifier: Intended Audience :: Science/Research
Classifier: Intended Audience :: System Administrators
Classifier: Programming Language :: Python :: 3
Classifier: Operating System :: Microsoft :: Windows
Classifier: Operating System :: MacOS
Classifier: Operating System :: Unix
Classifier: Topic :: Scientific/Engineering
Classifier: Topic :: Scientific/Engineering :: Information Analysis
Classifier: Topic :: Software Development :: Libraries :: Python Modules
Requires-Dist: pandas (==2.2.2)
